bma400.py
circuitpython_bma400-0.1.0.dist-info/LICENSE
circuitpython_bma400-0.1.0.dist-info/METADATA
circuitpython_bma400-0.1.0.dist-info/WHEEL
circuitpython_bma400-0.1.0.dist-info/top_level.txt
circuitpython_bma400-0.1.0.dist-info/RECORD
